ctstore
